[
  {
    "title": "Exactly what I needed!",
    "text": "The masonry image gallery works perfect on my Shopify site and has endless customization options.",
    "reviewer": "Anonymous",
    "productIndex": 2
  },
  {
    "title": "well done!",
    "text": "Precisely what I was looking for, great support!",
    "reviewer": "DC",
    "productIndex": 0
  },
  {
    "title": "LOVED the script for the Carousel & Grid",
    "text": "My theme did not support this. Researched and finally found what I needed for my store. Saved me a bunch!",
    "reviewer": "Susan S.",
    "productIndex": 1
  }
]
